src/__init__.py
src/backbone.py
src/helpers.py
src/main.py
seenovideos-1.2.1.dist-info/METADATA
seenovideos-1.2.1.dist-info/WHEEL
seenovideos-1.2.1.dist-info/top_level.txt
seenovideos-1.2.1.dist-info/RECORD
