Metadata-Version: 2.1
Name: seenovideos
Version: 1.2.1
Summary: Video editing in a text file
Home-page: https://github.com/SubhadityaMukherjee/seeNoVideo
Author: Subhaditya Mukherjee
Author-email: msubhaditya@gmail.com
License: GPLv3+
Platform: UNKNOWN
Classifier: Programming Language :: Python :: 3
Classifier: License :: OSI Approved :: MIT License
Classifier: Operating System :: OS Independent
